{
  "source": "meridian",
  "meridian_date": "2026-06-29",
  "generated_at_utc": "2026-06-29T23:47:59.255099+00:00",
  "regime": {
    "regime": "mid_vol_range",
    "tags": [
      "mid_vol",
      "range",
      "mixed_breadth"
    ],
    "names_explained": 504
  },
  "counts": {
    "flow_candidates": 86,
    "gamma_squeeze": 0,
    "price_before_news": 0,
    "sympathy_beta": 42
  },
  "notes": "EOD attribution of the prior session. Use as pre-market regime + watchlist + flow-confirmation overlay ONLY; not an intraday trigger. Lower residual = the labeled mechanism explains more of the move. Confidence is 0-1. Helm must still require its own intraday trigger and obey all RISK LIMITS.",
  "gamma_squeeze": [],
  "flow_candidates": [
    {
      "ticker": "MU",
      "move_pct": -0.08180478171358985,
      "pattern": "options_led_proxy",
      "tier": "Medium",
      "confidence": 0.50125,
      "residual": 0.304167,
      "residual_basis": "structural",
      "data_source": "live",
      "proxy_data": false,
      "move_class": "mixed",
      "initiating": "MU abnormal move -8.18%",
      "in_universe": true,
      "move_pct_display": -8.18
    },
    {
      "ticker": "PLTR",
      "move_pct": 0.033826261263625756,
      "pattern": "options_led_proxy",
      "tier": "Medium",
      "confidence": 0.487917,
      "residual": 0.316667,
      "residual_basis": "structural",
      "data_source": "live",
      "proxy_data": false,
      "move_class": "mixed",
      "initiating": "PLTR abnormal move +3.38%",
      "in_universe": true,
      "move_pct_display": 3.38
    },
    {
      "ticker": "NOW",
      "move_pct": 0.03299779202179742,
      "pattern": "options_led_proxy",
      "tier": "Medium",
      "confidence": 0.47125,
      "residual": 0.3375,
      "residual_basis": "structural",
      "data_source": "live",
      "proxy_data": false,
      "move_class": "mixed",
      "initiating": "NOW abnormal move +3.30%",
      "in_universe": true,
      "move_pct_display": 3.3
    },
    {
      "ticker": "MRVL",
      "move_pct": -0.05067992187627801,
      "pattern": "options_led_proxy",
      "tier": "Medium",
      "confidence": 0.4675,
      "residual": 0.341667,
      "residual_basis": "structural",
      "data_source": "live",
      "proxy_data": false,
      "move_class": "mixed",
      "initiating": "MRVL abnormal move -5.07%",
      "in_universe": true,
      "move_pct_display": -5.07
    },
    {
      "ticker": "CMCSA",
      "move_pct": 0.09861889684454406,
      "pattern": "options_led_proxy",
      "tier": "Medium",
      "confidence": 0.75625,
      "residual": 0.05,
      "residual_basis": "structural",
      "data_source": "live",
      "proxy_data": false,
      "move_class": "mixed",
      "initiating": "CMCSA abnormal move +9.86%",
      "in_universe": false,
      "move_pct_display": 9.86
    },
    {
      "ticker": "WMB",
      "move_pct": -0.040297734387009676,
      "pattern": "options_led_proxy",
      "tier": "Medium",
      "confidence": 0.547917,
      "residual": 0.25,
      "residual_basis": "structural",
      "data_source": "live",
      "proxy_data": false,
      "move_class": "mixed",
      "initiating": "WMB abnormal move -4.03%",
      "in_universe": false,
      "move_pct_display": -4.03
    },
    {
      "ticker": "HON",
      "move_pct": -0.47155593843258514,
      "pattern": "options_led_proxy",
      "tier": "Medium",
      "confidence": 0.54625,
      "residual": 0.254167,
      "residual_basis": "structural",
      "data_source": "live",
      "proxy_data": false,
      "move_class": "mixed",
      "initiating": "HON abnormal move -47.16%",
      "in_universe": false,
      "move_pct_display": -47.16
    },
    {
      "ticker": "MA",
      "move_pct": 0.025600225833263268,
      "pattern": "options_led_proxy",
      "tier": "Medium",
      "confidence": 0.53875,
      "residual": 0.2625,
      "residual_basis": "structural",
      "data_source": "live",
      "proxy_data": false,
      "move_class": "mixed",
      "initiating": "MA abnormal move +2.56%",
      "in_universe": false,
      "move_pct_display": 2.56
    },
    {
      "ticker": "V",
      "move_pct": 0.023466031802795273,
      "pattern": "options_led_proxy",
      "tier": "Medium",
      "confidence": 0.53875,
      "residual": 0.2625,
      "residual_basis": "structural",
      "data_source": "live",
      "proxy_data": false,
      "move_class": "mixed",
      "initiating": "V abnormal move +2.35%",
      "in_universe": false,
      "move_pct_display": 2.35
    },
    {
      "ticker": "AXON",
      "move_pct": 0.0920551809930823,
      "pattern": "options_led_proxy",
      "tier": "Medium",
      "confidence": 0.535,
      "residual": 0.266667,
      "residual_basis": "structural",
      "data_source": "live",
      "proxy_data": false,
      "move_class": "mixed",
      "initiating": "AXON abnormal move +9.21%",
      "in_universe": false,
      "move_pct_display": 9.21
    },
    {
      "ticker": "CPRT",
      "move_pct": -0.028805210564426642,
      "pattern": "options_led_proxy",
      "tier": "Medium",
      "confidence": 0.535,
      "residual": 0.266667,
      "residual_basis": "structural",
      "data_source": "live",
      "proxy_data": false,
      "move_class": "mixed",
      "initiating": "CPRT abnormal move -2.88%",
      "in_universe": false,
      "move_pct_display": -2.88
    },
    {
      "ticker": "FFIV",
      "move_pct": 0.03391378329711592,
      "pattern": "options_led_proxy",
      "tier": "Medium",
      "confidence": 0.53125,
      "residual": 0.270833,
      "residual_basis": "structural",
      "data_source": "live",
      "proxy_data": false,
      "move_class": "mixed",
      "initiating": "FFIV abnormal move +3.39%",
      "in_universe": false,
      "move_pct_display": 3.39
    },
    {
      "ticker": "PANW",
      "move_pct": 0.057988111186708435,
      "pattern": "options_led_proxy",
      "tier": "Medium",
      "confidence": 0.53125,
      "residual": 0.270833,
      "residual_basis": "structural",
      "data_source": "live",
      "proxy_data": false,
      "move_class": "mixed",
      "initiating": "PANW abnormal move +5.80%",
      "in_universe": false,
      "move_pct_display": 5.8
    },
    {
      "ticker": "AEE",
      "move_pct": -0.020875601986763415,
      "pattern": "options_led_proxy",
      "tier": "Medium",
      "confidence": 0.529167,
      "residual": 0.270833,
      "residual_basis": "structural",
      "data_source": "live",
      "proxy_data": false,
      "move_class": "mixed",
      "initiating": "AEE abnormal move -2.09%",
      "in_universe": false,
      "move_pct_display": -2.09
    },
    {
      "ticker": "KMI",
      "move_pct": -0.024254303660259047,
      "pattern": "options_led_proxy",
      "tier": "Medium",
      "confidence": 0.5275,
      "residual": 0.275,
      "residual_basis": "structural",
      "data_source": "live",
      "proxy_data": false,
      "move_class": "mixed",
      "initiating": "KMI abnormal move -2.43%",
      "in_universe": false,
      "move_pct_display": -2.43
    },
    {
      "ticker": "COHR",
      "move_pct": -0.08411291247366726,
      "pattern": "options_led_proxy",
      "tier": "Medium",
      "confidence": 0.52375,
      "residual": 0.279167,
      "residual_basis": "structural",
      "data_source": "live",
      "proxy_data": false,
      "move_class": "mixed",
      "initiating": "COHR abnormal move -8.41%",
      "in_universe": false,
      "move_pct_display": -8.41
    },
    {
      "ticker": "TAP",
      "move_pct": -0.024879404340717226,
      "pattern": "options_led_proxy",
      "tier": "Medium",
      "confidence": 0.52,
      "residual": 0.283333,
      "residual_basis": "structural",
      "data_source": "live",
      "proxy_data": false,
      "move_class": "mixed",
      "initiating": "TAP abnormal move -2.49%",
      "in_universe": false,
      "move_pct_display": -2.49
    },
    {
      "ticker": "CRWD",
      "move_pct": 0.055570553630955644,
      "pattern": "options_led_proxy",
      "tier": "Medium",
      "confidence": 0.52,
      "residual": 0.283333,
      "residual_basis": "structural",
      "data_source": "live",
      "proxy_data": false,
      "move_class": "mixed",
      "initiating": "CRWD abnormal move +5.56%",
      "in_universe": false,
      "move_pct_display": 5.56
    },
    {
      "ticker": "CASY",
      "move_pct": 0.02500542052197874,
      "pattern": "options_led_proxy",
      "tier": "Medium",
      "confidence": 0.5175,
      "residual": 0.279167,
      "residual_basis": "structural",
      "data_source": "live",
      "proxy_data": false,
      "move_class": "mixed",
      "initiating": "CASY abnormal move +2.50%",
      "in_universe": false,
      "move_pct_display": 2.5
    },
    {
      "ticker": "STZ",
      "move_pct": -0.030211880223827592,
      "pattern": "options_led_proxy",
      "tier": "Medium",
      "confidence": 0.51625,
      "residual": 0.2875,
      "residual_basis": "structural",
      "data_source": "live",
      "proxy_data": false,
      "move_class": "mixed",
      "initiating": "STZ abnormal move -3.02%",
      "in_universe": false,
      "move_pct_display": -3.02
    },
    {
      "ticker": "MPC",
      "move_pct": 0.0329445943670168,
      "pattern": "options_led_proxy",
      "tier": "Medium",
      "confidence": 0.515,
      "residual": 0.295833,
      "residual_basis": "structural",
      "data_source": "live",
      "proxy_data": false,
      "move_class": "mixed",
      "initiating": "MPC abnormal move +3.29%",
      "in_universe": false,
      "move_pct_display": 3.29
    },
    {
      "ticker": "MSI",
      "move_pct": 0.017275164938379994,
      "pattern": "options_led_proxy",
      "tier": "Medium",
      "confidence": 0.514167,
      "residual": 0.2875,
      "residual_basis": "structural",
      "data_source": "live",
      "proxy_data": false,
      "move_class": "mixed",
      "initiating": "MSI abnormal move +1.73%",
      "in_universe": false,
      "move_pct_display": 1.73
    },
    {
      "ticker": "UNP",
      "move_pct": 0.01792434301916246,
      "pattern": "options_led_proxy",
      "tier": "Medium",
      "confidence": 0.512917,
      "residual": 0.295833,
      "residual_basis": "structural",
      "data_source": "live",
      "proxy_data": false,
      "move_class": "mixed",
      "initiating": "UNP abnormal move +1.79%",
      "in_universe": false,
      "move_pct_display": 1.79
    },
    {
      "ticker": "CHD",
      "move_pct": -0.0210885562914922,
      "pattern": "options_led_proxy",
      "tier": "Medium",
      "confidence": 0.5125,
      "residual": 0.291667,
      "residual_basis": "structural",
      "data_source": "live",
      "proxy_data": false,
      "move_class": "mixed",
      "initiating": "CHD abnormal move -2.11%",
      "in_universe": false,
      "move_pct_display": -2.11
    },
    {
      "ticker": "MKC",
      "move_pct": 0.0220372187426654,
      "pattern": "options_led_proxy",
      "tier": "Medium",
      "confidence": 0.5125,
      "residual": 0.291667,
      "residual_basis": "structural",
      "data_source": "live",
      "proxy_data": false,
      "move_class": "mixed",
      "initiating": "MKC abnormal move +2.20%",
      "in_universe": false,
      "move_pct_display": 2.2
    },
    {
      "ticker": "CIEN",
      "move_pct": -0.06389992627411367,
      "pattern": "options_led_proxy",
      "tier": "Medium",
      "confidence": 0.510417,
      "residual": 0.291667,
      "residual_basis": "structural",
      "data_source": "live",
      "proxy_data": false,
      "move_class": "mixed",
      "initiating": "CIEN abnormal move -6.39%",
      "in_universe": false,
      "move_pct_display": -6.39
    },
    {
      "ticker": "VLO",
      "move_pct": 0.03161464429612959,
      "pattern": "options_led_proxy",
      "tier": "Medium",
      "confidence": 0.509583,
      "residual": 0.304167,
      "residual_basis": "structural",
      "data_source": "live",
      "proxy_data": false,
      "move_class": "mixed",
      "initiating": "VLO abnormal move +3.16%",
      "in_universe": false,
      "move_pct_display": 3.16
    },
    {
      "ticker": "TPL",
      "move_pct": 0.03276990560824378,
      "pattern": "options_led_proxy",
      "tier": "Medium",
      "confidence": 0.50875,
      "residual": 0.295833,
      "residual_basis": "structural",
      "data_source": "live",
      "proxy_data": false,
      "move_class": "mixed",
      "initiating": "TPL abnormal move +3.28%",
      "in_universe": false,
      "move_pct_display": 3.28
    },
    {
      "ticker": "UNH",
      "move_pct": -0.022540884809323036,
      "pattern": "options_led_proxy",
      "tier": "Medium",
      "confidence": 0.50875,
      "residual": 0.295833,
      "residual_basis": "structural",
      "data_source": "live",
      "proxy_data": false,
      "move_class": "mixed",
      "initiating": "UNH abnormal move -2.25%",
      "in_universe": false,
      "move_pct_display": -2.25
    },
    {
      "ticker": "PSX",
      "move_pct": 0.025487912354010378,
      "pattern": "options_led_proxy",
      "tier": "Medium",
      "confidence": 0.505417,
      "residual": 0.304167,
      "residual_basis": "structural",
      "data_source": "live",
      "proxy_data": false,
      "move_class": "mixed",
      "initiating": "PSX abnormal move +2.55%",
      "in_universe": false,
      "move_pct_display": 2.55
    },
    {
      "ticker": "INTC",
      "move_pct": -0.06682515654765164,
      "pattern": "options_led_proxy",
      "tier": "Medium",
      "confidence": 0.50125,
      "residual": 0.304167,
      "residual_basis": "structural",
      "data_source": "live",
      "proxy_data": false,
      "move_class": "mixed",
      "initiating": "INTC abnormal move -6.68%",
      "in_universe": false,
      "move_pct_display": -6.68
    },
    {
      "ticker": "Q",
      "move_pct": -0.04715544626412849,
      "pattern": "options_led_proxy",
      "tier": "Medium",
      "confidence": 0.50125,
      "residual": 0.304167,
      "residual_basis": "structural",
      "data_source": "live",
      "proxy_data": false,
      "move_class": "mixed",
      "initiating": "Q abnormal move -4.72%",
      "in_universe": false,
      "move_pct_display": -4.72
    },
    {
      "ticker": "DDOG",
      "move_pct": 0.0321349697366613,
      "pattern": "options_led_proxy",
      "tier": "Medium",
      "confidence": 0.500833,
      "residual": 0.3,
      "residual_basis": "structural",
      "data_source": "live",
      "proxy_data": false,
      "move_class": "mixed",
      "initiating": "DDOG abnormal move +3.21%",
      "in_universe": false,
      "move_pct_display": 3.21
    },
    {
      "ticker": "FSLR",
      "move_pct": -0.0449659081886471,
      "pattern": "options_led_proxy",
      "tier": "Medium",
      "confidence": 0.499583,
      "residual": 0.308333,
      "residual_basis": "structural",
      "data_source": "live",
      "proxy_data": false,
      "move_class": "mixed",
      "initiating": "FSLR abnormal move -4.50%",
      "in_universe": false,
      "move_pct_display": -4.5
    },
    {
      "ticker": "BEN",
      "move_pct": -0.022734034153315208,
      "pattern": "options_led_proxy",
      "tier": "Medium",
      "confidence": 0.497917,
      "residual": 0.3125,
      "residual_basis": "structural",
      "data_source": "live",
      "proxy_data": false,
      "move_class": "mixed",
      "initiating": "BEN abnormal move -2.27%",
      "in_universe": false,
      "move_pct_display": -2.27
    },
    {
      "ticker": "SNDK",
      "move_pct": -0.08235949632091744,
      "pattern": "options_led_proxy",
      "tier": "Medium",
      "confidence": 0.49375,
      "residual": 0.3125,
      "residual_basis": "structural",
      "data_source": "live",
      "proxy_data": false,
      "move_class": "mixed",
      "initiating": "SNDK abnormal move -8.24%",
      "in_universe": false,
      "move_pct_display": -8.24
    },
    {
      "ticker": "DELL",
      "move_pct": -0.043205035595311636,
      "pattern": "options_led_proxy",
      "tier": "Medium",
      "confidence": 0.49375,
      "residual": 0.3125,
      "residual_basis": "structural",
      "data_source": "live",
      "proxy_data": false,
      "move_class": "mixed",
      "initiating": "DELL abnormal move -4.32%",
      "in_universe": false,
      "move_pct_display": -4.32
    },
    {
      "ticker": "AES",
      "move_pct": -0.003067489847301541,
      "pattern": "options_led_proxy",
      "tier": "Medium",
      "confidence": 0.49375,
      "residual": 0.3125,
      "residual_basis": "structural",
      "data_source": "live",
      "proxy_data": false,
      "move_class": "mixed",
      "initiating": "AES abnormal move -0.31%",
      "in_universe": false,
      "move_pct_display": -0.31
    },
    {
      "ticker": "TROW",
      "move_pct": 0.011834590957683133,
      "pattern": "options_led_proxy",
      "tier": "Medium",
      "confidence": 0.49,
      "residual": 0.316667,
      "residual_basis": "structural",
      "data_source": "live",
      "proxy_data": false,
      "move_class": "mixed",
      "initiating": "TROW abnormal move +1.18%",
      "in_universe": false,
      "move_pct_display": 1.18
    },
    {
      "ticker": "APO",
      "move_pct": -0.024262428982746775,
      "pattern": "options_led_proxy",
      "tier": "Medium",
      "confidence": 0.49,
      "residual": 0.316667,
      "residual_basis": "structural",
      "data_source": "live",
      "proxy_data": false,
      "move_class": "mixed",
      "initiating": "APO abnormal move -2.43%",
      "in_universe": false,
      "move_pct_display": -2.43
    }
  ],
  "price_before_news": [],
  "sympathy_beta_deprioritize": [
    {
      "ticker": "AMZN",
      "move_pct": 0.05006619202165141,
      "pattern": "sector_sympathy",
      "tier": "Medium",
      "confidence": 0.633333,
      "residual": 0.41716,
      "residual_basis": "return",
      "data_source": "live",
      "proxy_data": false,
      "move_class": "informational",
      "initiating": "Headline: Prediction Markets Emerge in Japan, With Shopping Vouchers",
      "in_universe": true,
      "move_pct_display": 5.01
    },
    {
      "ticker": "GOOG",
      "move_pct": 0.032657063539550224,
      "pattern": "sector_sympathy",
      "tier": "High",
      "confidence": 0.729583,
      "residual": 0.350169,
      "residual_basis": "return",
      "data_source": "live",
      "proxy_data": false,
      "move_class": "mixed",
      "initiating": "GOOG abnormal move +3.27%",
      "in_universe": true,
      "move_pct_display": 3.27
    },
    {
      "ticker": "GOOGL",
      "move_pct": 0.03159540200275046,
      "pattern": "sector_sympathy",
      "tier": "Medium",
      "confidence": 0.624167,
      "residual": 0.428417,
      "residual_basis": "return",
      "data_source": "live",
      "proxy_data": false,
      "move_class": "informational",
      "initiating": "Headline: Alphabet\u2019s (GOOGL) Google Cloud Partners with Philippine Government to",
      "in_universe": true,
      "move_pct_display": 3.16
    },
    {
      "ticker": "META",
      "move_pct": 0.0303498631658905,
      "pattern": "sector_sympathy",
      "tier": "Medium",
      "confidence": 0.61875,
      "residual": 0.123629,
      "residual_basis": "return",
      "data_source": "live",
      "proxy_data": false,
      "move_class": "informational",
      "initiating": "Headline: Silicon Valley\u2019s AI jobs purge is a warning for the world",
      "in_universe": true,
      "move_pct_display": 3.03
    },
    {
      "ticker": "TSLA",
      "move_pct": 0.03033899499748327,
      "pattern": "sector_sympathy",
      "tier": "Medium",
      "confidence": 0.5675,
      "residual": 0.345985,
      "residual_basis": "return",
      "data_source": "live",
      "proxy_data": false,
      "move_class": "informational",
      "initiating": "Headline: Dow Jones Futures Rise On U.S.-Iran News; Market At Tipping Point",
      "in_universe": true,
      "move_pct_display": 3.03
    },
    {
      "ticker": "NFLX",
      "move_pct": 0.022015987721853092,
      "pattern": "sector_sympathy",
      "tier": "Medium",
      "confidence": 0.682917,
      "residual": 0.230208,
      "residual_basis": "return",
      "data_source": "live",
      "proxy_data": false,
      "move_class": "mixed",
      "initiating": "NFLX abnormal move +2.20%",
      "in_universe": true,
      "move_pct_display": 2.2
    },
    {
      "ticker": "CHTR",
      "move_pct": 0.14827149455181066,
      "pattern": "sector_sympathy",
      "tier": "High",
      "confidence": 0.760417,
      "residual": 0.740083,
      "residual_basis": "return",
      "data_source": "live",
      "proxy_data": false,
      "move_class": "mixed",
      "initiating": "CHTR abnormal move +14.83%",
      "in_universe": false,
      "move_pct_display": 14.83
    },
    {
      "ticker": "VZ",
      "move_pct": -0.06542763050584,
      "pattern": "sector_sympathy",
      "tier": "High",
      "confidence": 0.764167,
      "residual": 1.0,
      "residual_basis": "return",
      "data_source": "live",
      "proxy_data": false,
      "move_class": "mixed",
      "initiating": "VZ abnormal move -6.54%",
      "in_universe": false,
      "move_pct_display": -6.54
    },
    {
      "ticker": "MLM",
      "move_pct": -0.05262471681108105,
      "pattern": "sector_sympathy",
      "tier": "High",
      "confidence": 0.715417,
      "residual": 0.667174,
      "residual_basis": "return",
      "data_source": "live",
      "proxy_data": false,
      "move_class": "mixed",
      "initiating": "MLM abnormal move -5.26%",
      "in_universe": false,
      "move_pct_display": -5.26
    },
    {
      "ticker": "TMUS",
      "move_pct": -0.04581779862473767,
      "pattern": "sector_sympathy",
      "tier": "High",
      "confidence": 0.760417,
      "residual": 1.0,
      "residual_basis": "return",
      "data_source": "live",
      "proxy_data": false,
      "move_class": "mixed",
      "initiating": "TMUS abnormal move -4.58%",
      "in_universe": false,
      "move_pct_display": -4.58
    },
    {
      "ticker": "TTD",
      "move_pct": 0.04518235633029466,
      "pattern": "sector_sympathy",
      "tier": "Medium",
      "confidence": 0.68625,
      "residual": 0.578321,
      "residual_basis": "return",
      "data_source": "live",
      "proxy_data": false,
      "move_class": "mixed",
      "initiating": "TTD abnormal move +4.52%",
      "in_universe": false,
      "move_pct_display": 4.52
    },
    {
      "ticker": "T",
      "move_pct": -0.04423411932833454,
      "pattern": "sector_sympathy",
      "tier": "High",
      "confidence": 0.762083,
      "residual": 1.0,
      "residual_basis": "return",
      "data_source": "live",
      "proxy_data": false,
      "move_class": "mixed",
      "initiating": "T abnormal move -4.42%",
      "in_universe": false,
      "move_pct_display": -4.42
    },
    {
      "ticker": "CVNA",
      "move_pct": 0.03977551592022799,
      "pattern": "sector_sympathy",
      "tier": "Medium",
      "confidence": 0.666667,
      "residual": 0.123482,
      "residual_basis": "return",
      "data_source": "live",
      "proxy_data": false,
      "move_class": "mixed",
      "initiating": "CVNA abnormal move +3.98%",
      "in_universe": false,
      "move_pct_display": 3.98
    },
    {
      "ticker": "SW",
      "move_pct": -0.0370369919268565,
      "pattern": "sector_sympathy",
      "tier": "Medium",
      "confidence": 0.67625,
      "residual": 0.389956,
      "residual_basis": "return",
      "data_source": "live",
      "proxy_data": false,
      "move_class": "mixed",
      "initiating": "SW abnormal move -3.70%",
      "in_universe": false,
      "move_pct_display": -3.7
    },
    {
      "ticker": "DRI",
      "move_pct": -0.03608690741359244,
      "pattern": "sector_sympathy",
      "tier": "High",
      "confidence": 0.737083,
      "residual": 1.0,
      "residual_basis": "return",
      "data_source": "live",
      "proxy_data": false,
      "move_class": "mixed",
      "initiating": "DRI abnormal move -3.61%",
      "in_universe": false,
      "move_pct_display": -3.61
    },
    {
      "ticker": "MELI",
      "move_pct": 0.035159107151588875,
      "pattern": "sector_sympathy",
      "tier": "High",
      "confidence": 0.712917,
      "residual": 0.375462,
      "residual_basis": "return",
      "data_source": "live",
      "proxy_data": false,
      "move_class": "mixed",
      "initiating": "MELI abnormal move +3.52%",
      "in_universe": false,
      "move_pct_display": 3.52
    },
    {
      "ticker": "ECHO",
      "move_pct": 0.03422398866615439,
      "pattern": "sector_sympathy",
      "tier": "Medium",
      "confidence": 0.689583,
      "residual": 0.511555,
      "residual_basis": "return",
      "data_source": "live",
      "proxy_data": false,
      "move_class": "mixed",
      "initiating": "ECHO abnormal move +3.42%",
      "in_universe": false,
      "move_pct_display": 3.42
    },
    {
      "ticker": "CRH",
      "move_pct": -0.034188001676673574,
      "pattern": "sector_sympathy",
      "tier": "Medium",
      "confidence": 0.68375,
      "residual": 0.436509,
      "residual_basis": "return",
      "data_source": "live",
      "proxy_data": false,
      "move_class": "mixed",
      "initiating": "CRH abnormal move -3.42%",
      "in_universe": false,
      "move_pct_display": -3.42
    },
    {
      "ticker": "OMC",
      "move_pct": 0.03372559981929113,
      "pattern": "sector_sympathy",
      "tier": "High",
      "confidence": 0.75125,
      "residual": 0.710111,
      "residual_basis": "return",
      "data_source": "live",
      "proxy_data": false,
      "move_class": "mixed",
      "initiating": "OMC abnormal move +3.37%",
      "in_universe": false,
      "move_pct_display": 3.37
    },
    {
      "ticker": "TTWO",
      "move_pct": 0.03370648801436915,
      "pattern": "sector_sympathy",
      "tier": "High",
      "confidence": 0.729583,
      "residual": 0.600806,
      "residual_basis": "return",
      "data_source": "live",
      "proxy_data": false,
      "move_class": "mixed",
      "initiating": "TTWO abnormal move +3.37%",
      "in_universe": false,
      "move_pct_display": 3.37
    },
    {
      "ticker": "ULTA",
      "move_pct": -0.03318665486241312,
      "pattern": "sector_sympathy",
      "tier": "High",
      "confidence": 0.722083,
      "residual": 1.0,
      "residual_basis": "return",
      "data_source": "live",
      "proxy_data": false,
      "move_class": "mixed",
      "initiating": "ULTA abnormal move -3.32%",
      "in_universe": false,
      "move_pct_display": -3.32
    },
    {
      "ticker": "DOW",
      "move_pct": -0.03133614759199865,
      "pattern": "sector_sympathy",
      "tier": "Medium",
      "confidence": 0.681667,
      "residual": 1.0,
      "residual_basis": "return",
      "data_source": "live",
      "proxy_data": false,
      "move_class": "mixed",
      "initiating": "DOW abnormal move -3.13%",
      "in_universe": false,
      "move_pct_display": -3.13
    },
    {
      "ticker": "DD",
      "move_pct": -0.03038914248541902,
      "pattern": "sector_sympathy",
      "tier": "Medium",
      "confidence": 0.687083,
      "residual": 0.412841,
      "residual_basis": "return",
      "data_source": "live",
      "proxy_data": false,
      "move_class": "mixed",
      "initiating": "DD abnormal move -3.04%",
      "in_universe": false,
      "move_pct_display": -3.04
    },
    {
      "ticker": "WY",
      "move_pct": -0.03002766672929036,
      "pattern": "sector_sympathy",
      "tier": "Medium",
      "confidence": 0.640833,
      "residual": 0.750821,
      "residual_basis": "return",
      "data_source": "live",
      "proxy_data": false,
      "move_class": "mixed",
      "initiating": "WY abnormal move -3.00%",
      "in_universe": false,
      "move_pct_display": -3.0
    },
    {
      "ticker": "APTV",
      "move_pct": -0.02884611857713304,
      "pattern": "sector_sympathy",
      "tier": "Medium",
      "confidence": 0.631667,
      "residual": 1.0,
      "residual_basis": "return",
      "data_source": "live",
      "proxy_data": false,
      "move_class": "mixed",
      "initiating": "APTV abnormal move -2.88%",
      "in_universe": false,
      "move_pct_display": -2.88
    },
    {
      "ticker": "CCI",
      "move_pct": -0.028322487164065824,
      "pattern": "sector_sympathy",
      "tier": "Medium",
      "confidence": 0.6075,
      "residual": 0.543297,
      "residual_basis": "return",
      "data_source": "live",
      "proxy_data": false,
      "move_class": "mixed",
      "initiating": "CCI abnormal move -2.83%",
      "in_universe": false,
      "move_pct_display": -2.83
    },
    {
      "ticker": "IP",
      "move_pct": -0.026831711709654704,
      "pattern": "sector_sympathy",
      "tier": "Medium",
      "confidence": 0.638333,
      "residual": 0.297843,
      "residual_basis": "return",
      "data_source": "live",
      "proxy_data": false,
      "move_class": "mixed",
      "initiating": "IP abnormal move -2.68%",
      "in_universe": false,
      "move_pct_display": -2.68
    },
    {
      "ticker": "ALB",
      "move_pct": -0.026813698854951662,
      "pattern": "sector_sympathy",
      "tier": "Medium",
      "confidence": 0.609167,
      "residual": 0.139623,
      "residual_basis": "return",
      "data_source": "live",
      "proxy_data": false,
      "move_class": "mixed",
      "initiating": "ALB abnormal move -2.68%",
      "in_universe": false,
      "move_pct_display": -2.68
    },
    {
      "ticker": "ABNB",
      "move_pct": 0.02648462904453308,
      "pattern": "sector_sympathy",
      "tier": "High",
      "confidence": 0.706667,
      "residual": 0.131207,
      "residual_basis": "return",
      "data_source": "live",
      "proxy_data": false,
      "move_class": "mixed",
      "initiating": "ABNB abnormal move +2.65%",
      "in_universe": false,
      "move_pct_display": 2.65
    },
    {
      "ticker": "EXPE",
      "move_pct": 0.026369952493372262,
      "pattern": "sector_sympathy",
      "tier": "Medium",
      "confidence": 0.640417,
      "residual": 0.082912,
      "residual_basis": "return",
      "data_source": "live",
      "proxy_data": false,
      "move_class": "mixed",
      "initiating": "EXPE abnormal move +2.64%",
      "in_universe": false,
      "move_pct_display": 2.64
    },
    {
      "ticker": "NEM",
      "move_pct": -0.026006450342545007,
      "pattern": "sector_sympathy",
      "tier": "Medium",
      "confidence": 0.60375,
      "residual": 0.177133,
      "residual_basis": "return",
      "data_source": "live",
      "proxy_data": false,
      "move_class": "mixed",
      "initiating": "NEM abnormal move -2.60%",
      "in_universe": false,
      "move_pct_display": -2.6
    },
    {
      "ticker": "LULU",
      "move_pct": -0.02560178739511365,
      "pattern": "sector_sympathy",
      "tier": "Medium",
      "confidence": 0.632917,
      "residual": 1.0,
      "residual_basis": "return",
      "data_source": "live",
      "proxy_data": false,
      "move_class": "mixed",
      "initiating": "LULU abnormal move -2.56%",
      "in_universe": false,
      "move_pct_display": -2.56
    },
    {
      "ticker": "FCX",
      "move_pct": -0.025300269203396564,
      "pattern": "sector_sympathy",
      "tier": "Medium",
      "confidence": 0.600417,
      "residual": 0.200143,
      "residual_basis": "return",
      "data_source": "live",
      "proxy_data": false,
      "move_class": "mixed",
      "initiating": "FCX abnormal move -2.53%",
      "in_universe": false,
      "move_pct_display": -2.53
    },
    {
      "ticker": "SBAC",
      "move_pct": -0.024978213295059004,
      "pattern": "sector_sympathy",
      "tier": "Medium",
      "confidence": 0.59875,
      "residual": 0.375944,
      "residual_basis": "return",
      "data_source": "live",
      "proxy_data": false,
      "move_class": "mixed",
      "initiating": "SBAC abnormal move -2.50%",
      "in_universe": false,
      "move_pct_display": -2.5
    },
    {
      "ticker": "ORLY",
      "move_pct": 0.023562261735848633,
      "pattern": "sector_sympathy",
      "tier": "High",
      "confidence": 0.710833,
      "residual": 0.735334,
      "residual_basis": "return",
      "data_source": "live",
      "proxy_data": false,
      "move_class": "mixed",
      "initiating": "ORLY abnormal move +2.36%",
      "in_universe": false,
      "move_pct_display": 2.36
    },
    {
      "ticker": "EBAY",
      "move_pct": 0.022897872702491107,
      "pattern": "sector_sympathy",
      "tier": "Medium",
      "confidence": 0.647083,
      "residual": 0.657628,
      "residual_basis": "return",
      "data_source": "live",
      "proxy_data": false,
      "move_class": "mixed",
      "initiating": "EBAY abnormal move +2.29%",
      "in_universe": false,
      "move_pct_display": 2.29
    },
    {
      "ticker": "AZO",
      "move_pct": 0.0225141248779277,
      "pattern": "sector_sympathy",
      "tier": "Medium",
      "confidence": 0.6675,
      "residual": 0.581533,
      "residual_basis": "return",
      "data_source": "live",
      "proxy_data": false,
      "move_class": "mixed",
      "initiating": "AZO abnormal move +2.25%",
      "in_universe": false,
      "move_pct_display": 2.25
    },
    {
      "ticker": "CMG",
      "move_pct": -0.022495500796864354,
      "pattern": "sector_sympathy",
      "tier": "Medium",
      "confidence": 0.65125,
      "residual": 1.0,
      "residual_basis": "return",
      "data_source": "live",
      "proxy_data": false,
      "move_class": "mixed",
      "initiating": "CMG abnormal move -2.25%",
      "in_universe": false,
      "move_pct_display": -2.25
    },
    {
      "ticker": "PSKY",
      "move_pct": 0.02230282066976219,
      "pattern": "sector_sympathy",
      "tier": "Medium",
      "confidence": 0.64375,
      "residual": 0.366508,
      "residual_basis": "return",
      "data_source": "live",
      "proxy_data": false,
      "move_class": "mixed",
      "initiating": "PSKY abnormal move +2.23%",
      "in_universe": false,
      "move_pct_display": 2.23
    },
    {
      "ticker": "STLD",
      "move_pct": -0.021833885251596574,
      "pattern": "sector_sympathy",
      "tier": "Medium",
      "confidence": 0.63125,
      "residual": 0.36317,
      "residual_basis": "return",
      "data_source": "live",
      "proxy_data": false,
      "move_class": "mixed",
      "initiating": "STLD abnormal move -2.18%",
      "in_universe": false,
      "move_pct_display": -2.18
    }
  ]
}